phtool/__init__.py
phtool/__main__.py
phtool/align.py
phtool/biascomb.py
phtool/diffcali.py
phtool/find.py
phtool/flatcomb.py
phtool/imcorr.py
phtool/offset.py
phtool/phot.py
phtool/pick.py
phtool/util.py
phtool/xyget.py
phtool-0.25.717.dist-info/LICENSE
phtool-0.25.717.dist-info/METADATA
phtool-0.25.717.dist-info/WHEEL
phtool-0.25.717.dist-info/entry_points.txt
phtool-0.25.717.dist-info/top_level.txt
phtool-0.25.717.dist-info/RECORD
