Metadata-Version: 2.1
Name: phtool
Version: 0.25.717
Summary: Photometry Tools
Home-page: https://github.com/drjiezheng/phtool
Author: Dr Jie Zheng & Dr Lin-Qiao Jiang
Author-email: jiezheng@nao.cas.cn
Classifier: Development Status :: 3 - Alpha
Classifier: Intended Audience :: Science/Research
Classifier: License :: OSI Approved :: MIT License
Classifier: Operating System :: POSIX
Classifier: Operating System :: MacOS
Classifier: Programming Language :: Python :: 3 :: Only
Classifier: Topic :: Scientific/Engineering :: Astronomy
Requires-Python: >=3.10
License-File: LICENSE
Requires-Dist: numpy
Requires-Dist: scipy
Requires-Dist: matplotlib
Requires-Dist: astropy
Requires-Dist: photutils
Requires-Dist: astroalign
Requires-Dist: tqdm
Requires-Dist: qastutil
Requires-Dist: qmatch
